DataPipelineExecutor.py
DataPipelineExecutor-0.0.5.dist-info/LICENSE.txt
DataPipelineExecutor-0.0.5.dist-info/METADATA
DataPipelineExecutor-0.0.5.dist-info/WHEEL
DataPipelineExecutor-0.0.5.dist-info/top_level.txt
DataPipelineExecutor-0.0.5.dist-info/RECORD
