Metadata-Version: 2.1
Name: DataPipelineExecutor
Version: 0.0.5
Summary: A package to execute Copy and Stored Procedure tasks on data
Classifier: Programming Language :: Python :: 3
Classifier: License :: OSI Approved :: MIT License
Classifier: Operating System :: OS Independent
License-File: LICENSE.txt
